shift/__init__.py
shift/constants.py
shift/data_model.py
shift/exceptions.py
shift/openstreet_roads.py
shift/parcel.py
shift/plot_manager.py
shift/plots.py
shift/system_builder.py
shift/version.py
shift/graph/__init__.py
shift/graph/base_graph_builder.py
shift/graph/distribution_graph.py
shift/graph/openstreet_graph_builder.py
shift/graph/prsgb.py
shift/mapper/__init__.py
shift/mapper/balanced_phase_mapper.py
shift/mapper/base_equipment_mapper.py
shift/mapper/base_phase_mapper.py
shift/mapper/base_voltage_mapper.py
shift/mapper/edge_equipment_mapper.py
shift/mapper/transformer_voltage_mapper.py
shift/mcp_server/__init__.py
shift/mcp_server/config.py
shift/mcp_server/server.py
shift/mcp_server/state.py
shift/mcp_server/tools.py
shift/utils/__init__.py
shift/utils/get_cluster.py
shift/utils/mesh_network.py
shift/utils/nearest_points.py
shift/utils/polygon_from_points.py
shift/utils/split_network_edges.py
nrel_shift-0.6.1.dist-info/METADATA
nrel_shift-0.6.1.dist-info/WHEEL
nrel_shift-0.6.1.dist-info/entry_points.txt
nrel_shift-0.6.1.dist-info/licenses/LICENSE.txt
nrel_shift-0.6.1.dist-info/RECORD
