Metadata-Version: 2.4
Name: nrel-shift
Version: 0.6.1
Summary: Framework for developing synthetic distribution feeder model.
Project-URL: Documentation, https://github.com/NREL-Distribution-Suites/shift#readme
Project-URL: Issues, https://github.com/NREL-Distribution-Suites/shift/issues
Project-URL: Source, https://github.com/NREL-Distribution-Suites/shift
Author-email: Kapil Duwadi <Kapil.Duwadi@nrel.gov>, Aadil Latif <Aadil.Latif@nrel.gov>, Erik Pohl <Erik.Pohl@nrel.gov>
License-Expression: BSD-3-Clause
License-File: LICENSE.txt
Classifier: License :: OSI Approved :: BSD License
Classifier: Operating System :: OS Independent
Classifier: Programming Language :: Python :: 3.11
Requires-Python: >=3.10
Requires-Dist: geopy
Requires-Dist: grid-data-models==2.2.1
Requires-Dist: importlib-metadata
Requires-Dist: loguru
Requires-Dist: osmnx
Requires-Dist: plotly
Requires-Dist: scikit-learn
Provides-Extra: dev
Requires-Dist: pre-commit; extra == 'dev'
Requires-Dist: pytest; extra == 'dev'
Requires-Dist: pytest-cov; extra == 'dev'
Requires-Dist: pytest-mock; extra == 'dev'
Requires-Dist: ruff; extra == 'dev'
Provides-Extra: doc
Requires-Dist: autodoc-pydantic; extra == 'doc'
Requires-Dist: myst-parser; extra == 'doc'
Requires-Dist: pydata-sphinx-theme; extra == 'doc'
Requires-Dist: sphinx; extra == 'doc'
Provides-Extra: mcp
Requires-Dist: mcp>=0.9.0; extra == 'mcp'
Requires-Dist: pyyaml; extra == 'mcp'
